django_query_prefixer/__init__.py
django_query_prefixer/cursor.py
django_query_prefixer/backends/mysql/base.py
django_query_prefixer/backends/postgis/base.py
django_query_prefixer/backends/postgresql/base.py
django_query_prefixer/backends/sqlite3/base.py
django_query_prefixer/middlewares/__init__.py
django_query_prefixer-0.1.3.dist-info/METADATA
django_query_prefixer-0.1.3.dist-info/WHEEL
django_query_prefixer-0.1.3.dist-info/licenses/LICENSE
django_query_prefixer-0.1.3.dist-info/RECORD
