Metadata-Version: 2.1
Name: django-query-prefixer
Version: 0.1.3
Summary: Add helpful annotations to SQL queries.
Project-URL: Source, https://github.com/ecarrara/django-query-prefixer
Project-URL: Issues, https://github.com/ecarrara/django-query-prefixer/issues
Author-email: Erle Carrara <carrara.erle@gmail.com>
License-File: LICENSE
Classifier: Framework :: Django
Classifier: Framework :: Django :: 4
Classifier: License :: OSI Approved :: MIT License
Classifier: Operating System :: OS Independent
Classifier: Programming Language :: Python :: 3
Requires-Python: >=3.8
